<?xml version="1.0" encoding="UTF-8"?><hc:HRTRANSTx xmlns:p="us:gov:federal:hc:codes" xmlns:hc="us:gov:federal:hc" xmlns:xsi="http://www.w3.org/2001/XMLSchema-instance" hc:DestinationSystem="IBC" hc:EnumVersion="4.0" hc:ID="20" hc:SSP="IBC" hc:SSPProvider="IBC" hc:TxTime="2022-04-14T09:59:02" hc:Version="4.0" xsi:schemaLocation="us:gov:federal:hc HRTRANS.xsd"><hc:HRTRANSBatch hc:BatchType="P" hc:ID="20" hc:SummaryCount="1" hc:TxTime="2022-04-14T09:59:02"><hc:HRTRANSData hc:PAEffDate="2021-03-13" hc:PAEffSeqNum="11" hc:RecordID="00001565"><hc:HRTRANSEmployee hc:AlternatePersonID="00001565" hc:DOB="1982-07-05" hc:Gender="M" hc:GivenName="Will" hc:LastName="One" hc:MaritalStatus="S" hc:MiddleName="NMN" hc:SSN="310001030" hc:W4StandardDeductionIndicator="Yes"/><hc:HRTRANSFirstNOA hc:LAC1Code="RPM" hc:LAC1Desc="Reg 715.202.  Resignation" hc:NOACode="317" hc:NOADesc="Resignation" hc:SSPNOACode="317"/><hc:HRTRANSToPosition hc:AdjBasicPay="0" hc:AgySubElementCode="GS28" hc:BargUnitStatus="8888" hc:BasicPay="14.3" hc:DutyStationCode="221690071" hc:FLSA="N" hc:Grade="03" hc:OccSeries="4102" hc:OrgCode="ISE" hc:POI="1155" hc:PRD="0" hc:PayBasis="PH" hc:PayPlan="WL" hc:PayTableID="0061" hc:PosApprText="105.S00I0321.50.11.H40.." hc:PosNumber="90001204" hc:PosOrgTitle="Painter Leader" hc:PosTitle="Painter Leader" hc:SSPPayTableID="0061" hc:SteporRate="01" hc:TODHrs="40" hc:TotalSalary="14" hc:WorkSchedule="F"/><hc:HRTRANSEmployeeWork hc:AnnuitantInd="9" hc:FEGLI="C0" hc:RetirementPlan="K" hc:SCDLeave="2021-01-31" hc:SCDRetirement="2021-01-31" hc:TypeOfAppt="20" hc:VetPref="1" hc:VetPrefRIF="N"/><hc:HRTRANSEmployeeAddress hc:AddrCity="New Orleans" hc:AddrLine="3505 Main St" hc:AddrPostalCode="70130" hc:AddrState="LA" hc:AddrType="002" hc:CountryCode="US"/><hc:HRTRANSAgencyData hc:AgySubElementCode="GS28" hc:AgySubdivision="Office of GSA IT" hc:PAApprovalDate="2021-06-03" hc:PAAuthorizerTitle="Assistant Human Resources Office" hc:POI="1155" hc:PersonSignatureInd="Y"/><hc:HRTRANSRemark hc:AgencyUseRemarks="SF 2819 was provided.  Life insurance coverage is extended for 31 days during which you are eligible to convert to an individual policy (nongroup contract)." hc:AgencyUseRemarksCode="B46"/><hc:HRTRANSRemark hc:AgencyUseRemarks="Health benefits coverage is extended for 31 days during which you are eligible to convert to an individual policy (nongroup contract). You are also eligible for temporary continuation of your FEHB coverage for up to 18 months." hc:AgencyUseRemarksCode="B53"/><hc:HRTRANSRemark hc:AgencyUseRemarks="Forwarding address: 601 Poydras St New Orleans, LA 70130" hc:AgencyUseRemarksCode="M67"/><hc:HRTRANSRemark hc:AgencyUseRemarks="Lump-sum payment to be made for any unused annual leave." hc:AgencyUseRemarksCode="N27"/><hc:HRTRANSRemark hc:AgencyUseRemarks="OPF retained by www.archives.gov" hc:AgencyUseRemarksCode="N59"/><hc:HRTRANSRemark hc:AgencyUseRemarks="Employee gave no reason for resignation." hc:AgencyUseRemarksCode="S68"/><hc:HRTRANSRemark hc:AgencyUseRemarks="Not entitled to severance pay." hc:AgencyUseRemarksCode="N23"/><hc:HRTRANSRemark hc:AgencyUseRemarks="SF-8 issued to employee." hc:SSPRemarksCode="YS0"/><hc:HRTRANSTSP hc:TSPAcctTypeCode="1" hc:TSPSCD="2021-01-31"/><hc:HRTRANSFEHB hc:FEHBCode="F51"/></hc:HRTRANSData><hc:HRTRANSData hc:PAEffDate="2021-03-13" hc:PAEffSeqNum="11" hc:RecordID="00001582"><hc:HRTRANSEmployee hc:AlternatePersonID="00001582" hc:DOB="1994-10-29" hc:Gender="M" hc:GivenName="Slade" hc:LastName="Three" hc:MaritalStatus="S" hc:MiddleName="NMN" hc:SSN="310001062" hc:W4StandardDeductionIndicator="Yes"/><hc:HRTRANSFirstNOA hc:LAC1Code="DBM" hc:LAC1Desc="5 CFR part 715 / agy auth" hc:NOACode="352" hc:NOADesc="Termination-Appt in" hc:SSPNOACode="352"/><hc:HRTRANSToPosition hc:AdjBasicPay="0" hc:AgySubElementCode="GS28" hc:BargUnitStatus="8888" hc:BasicPay="140000" hc:DutyStationCode="274760053" hc:FLSA="E" hc:Grade="17" hc:OccSeries="0343" hc:OrgCode="ISE" hc:POI="1155" hc:PRD="0" hc:PayBasis="PA" hc:PayPlan="SL" hc:PayTableID="0000" hc:PosApprText="105.S00I0321.50.11.H40.." hc:PosNumber="90001226" hc:PosOrgTitle="Senior Data Advisor" hc:PosTitle="Senior Data Advisor" hc:SSPPayTableID="0000" hc:SteporRate="00" hc:TODHrs="40" hc:TotalSalary="140000" hc:WorkSchedule="F"/><hc:HRTRANSEmployeeWork hc:AnnuitantInd="9" hc:FEGLI="C0" hc:RetirementPlan="K" hc:SCDLeave="2021-01-31" hc:SCDRetirement="2021-01-31" hc:TypeOfAppt="20" hc:VetPref="1" hc:VetPrefRIF="N"/><hc:HRTRANSEmployeeAddress hc:AddrCity="Jonesboro" hc:AddrLine="3684 Main St" hc:AddrPostalCode="72401" hc:AddrState="AR" hc:AddrType="002" hc:CountryCode="US"/><hc:HRTRANSAgencyData hc:AgySubElementCode="GS28" hc:AgySubdivision="Office of GSA IT" hc:PAApprovalDate="2021-06-02" hc:PAAuthorizerTitle="Assistant Human Resources Office" hc:POI="1155" hc:PersonSignatureInd="Y"/><hc:HRTRANSRemark hc:AgencyUseRemarks="Forwarding address: 105 Main St., AR 72401" hc:AgencyUseRemarksCode="M67"/><hc:HRTRANSTSP hc:TSPAcctTypeCode="1" hc:TSPSCD="2021-01-31"/><hc:HRTRANSFEHB hc:FEHBCode="Z26"/></hc:HRTRANSData></hc:HRTRANSBatch></hc:HRTRANSTx>
